<?xml version="1.0" encoding="UTF-8"?>

<!-- generated on 2025-07-26 20:48:50 by Eclipse SUMO sumo Version 1.22.0
<sumoConfiguration xmlns:xsi="http://www.w3.org/2001/XMLSchema-instance" xsi:noNamespaceSchemaLocation="http://sumo.dlr.de/xsd/sumoConfiguration.xsd">

    <input>
        <net-file value="G:\python_learn\AIP\simulations/testmodel4/osm.net.xml.gz"/>
        <route-files value="G:\python_learn\AIP\simulations/testmodel4/osm.res_motorcycle.trips.xml,G:\python_learn\AIP\simulations/testmodel4/osm.res_bike.rou.xml,G:\python_learn\AIP\simulations/testmodel4/osm.res_truck.rou.xml,G:\python_learn\AIP\simulations/testmodel4/osm.res_veh.rou.xml,G:\python_learn\AIP\simulations/testmodel4/osm.res_ped.rou.xml"/>
        <additional-files value="G:\python_learn\AIP\simulations/testmodel4/osm.add.xml"/>
    </input>

    <processing>
        <waiting-time-memory value="3600"/>
    </processing>

    <report>
        <no-warnings value="true"/>
        <duration-log.disable value="true"/>
        <no-step-log value="true"/>
    </report>

    <traci_server>
        <remote-port value="55619"/>
    </traci_server>

</sumoConfiguration>
-->

<detector xmlns:xsi="http://www.w3.org/2001/XMLSchema-instance" xsi:noNamespaceSchemaLocation="http://sumo.dlr.de/xsd/det_e2_file.xsd">
   <interval begin="0.00" end="300.00" id="e2_49" sampledSeconds="53.96" nVehEntered="4" nVehLeft="3" nVehSeen="4" meanSpeed="5.98" meanTimeLoss="7.59" meanOccupancy="0.72" maxOccupancy="5.00" meanMaxJamLengthInVehicles="0.08" meanMaxJamLengthInMeters="0.40" maxJamLengthInVehicles="1" maxJamLengthInMeters="5.00" jamLengthInVehiclesSum="24" jamLengthInMetersSum="120.00" meanHaltingDuration="13.00" maxHaltingDuration="25.00" haltingDurationSum="26.00" meanIntervalHaltingDuration="13.00" maxIntervalHaltingDuration="25.00" intervalHaltingDurationSum="26.00" startedHalts="2.00" meanVehicleNumber="0.19" maxVehicleNumber="1" />
   <interval begin="300.00" end="600.00" id="e2_49" sampledSeconds="1065.21" nVehEntered="18" nVehLeft="16" nVehSeen="19" meanSpeed="1.63" meanTimeLoss="49.62" meanOccupancy="9.45" maxOccupancy="18.20" meanMaxJamLengthInVehicles="2.84" meanMaxJamLengthInMeters="12.17" maxJamLengthInVehicles="7" maxJamLengthInMeters="33.27" jamLengthInVehiclesSum="852" jamLengthInMetersSum="3652.26" meanHaltingDuration="36.04" maxHaltingDuration="134.00" haltingDurationSum="901.00" meanIntervalHaltingDuration="35.04" maxIntervalHaltingDuration="134.00" intervalHaltingDurationSum="876.00" startedHalts="24.00" meanVehicleNumber="3.59" maxVehicleNumber="7" />
   <interval begin="600.00" end="900.00" id="e2_49" sampledSeconds="1649.80" nVehEntered="20" nVehLeft="12" nVehSeen="23" meanSpeed="1.00" meanTimeLoss="65.63" meanOccupancy="14.84" maxOccupancy="28.60" meanMaxJamLengthInVehicles="4.71" meanMaxJamLengthInMeters="21.59" maxJamLengthInVehicles="12" maxJamLengthInMeters="54.20" jamLengthInVehiclesSum="1413" jamLengthInMetersSum="6476.27" meanHaltingDuration="66.91" maxHaltingDuration="178.00" haltingDurationSum="1472.00" meanIntervalHaltingDuration="65.09" maxIntervalHaltingDuration="178.00" intervalHaltingDurationSum="1432.00" startedHalts="19.00" meanVehicleNumber="5.55" maxVehicleNumber="12" />
   <interval begin="900.00" end="1200.00" id="e2_49" sampledSeconds="507.39" nVehEntered="25" nVehLeft="36" nVehSeen="36" meanSpeed="5.74" meanTimeLoss="8.16" meanOccupancy="5.05" maxOccupancy="31.00" meanMaxJamLengthInVehicles="0.52" meanMaxJamLengthInMeters="2.50" maxJamLengthInVehicles="7" maxJamLengthInMeters="37.09" jamLengthInVehiclesSum="157" jamLengthInMetersSum="750.56" meanHaltingDuration="25.45" maxHaltingDuration="151.00" haltingDurationSum="560.00" meanIntervalHaltingDuration="7.77" maxIntervalHaltingDuration="24.00" intervalHaltingDurationSum="171.00" startedHalts="14.00" meanVehicleNumber="1.79" maxVehicleNumber="11" />
   <interval begin="1200.00" end="1500.00" id="e2_49" sampledSeconds="1696.95" nVehEntered="18" nVehLeft="18" nVehSeen="18" meanSpeed="1.02" meanTimeLoss="87.46" meanOccupancy="19.50" maxOccupancy="49.10" meanMaxJamLengthInVehicles="4.87" meanMaxJamLengthInMeters="27.89" maxJamLengthInVehicles="15" maxJamLengthInMeters="84.13" jamLengthInVehiclesSum="1462" jamLengthInMetersSum="8367.40" meanHaltingDuration="98.47" maxHaltingDuration="159.00" haltingDurationSum="1477.00" meanIntervalHaltingDuration="98.47" maxIntervalHaltingDuration="159.00" intervalHaltingDurationSum="1477.00" startedHalts="15.00" meanVehicleNumber="5.71" maxVehicleNumber="15" />
   <interval begin="1500.00" end="1800.00" id="e2_49" sampledSeconds="580.66" nVehEntered="14" nVehLeft="13" nVehSeen="14" meanSpeed="2.41" meanTimeLoss="33.60" meanOccupancy="4.98" maxOccupancy="21.00" meanMaxJamLengthInVehicles="1.43" meanMaxJamLengthInMeters="5.69" maxJamLengthInVehicles="6" maxJamLengthInMeters="31.31" jamLengthInVehiclesSum="429" jamLengthInMetersSum="1706.53" meanHaltingDuration="62.28" maxHaltingDuration="165.00" haltingDurationSum="436.00" meanIntervalHaltingDuration="62.28" maxIntervalHaltingDuration="165.00" intervalHaltingDurationSum="436.00" startedHalts="7.00" meanVehicleNumber="1.98" maxVehicleNumber="7" />
   <interval begin="1800.00" end="2100.00" id="e2_49" sampledSeconds="166.30" nVehEntered="8" nVehLeft="7" nVehSeen="9" meanSpeed="5.13" meanTimeLoss="11.60" meanOccupancy="1.38" maxOccupancy="7.20" meanMaxJamLengthInVehicles="0.29" meanMaxJamLengthInMeters="0.98" maxJamLengthInVehicles="2" maxJamLengthInMeters="6.99" jamLengthInVehiclesSum="88" jamLengthInMetersSum="293.74" meanHaltingDuration="30.33" maxHaltingDuration="43.00" haltingDurationSum="91.00" meanIntervalHaltingDuration="30.33" maxIntervalHaltingDuration="43.00" intervalHaltingDurationSum="91.00" startedHalts="3.00" meanVehicleNumber="0.58" maxVehicleNumber="2" />
   <interval begin="2100.00" end="2400.00" id="e2_49" sampledSeconds="957.56" nVehEntered="23" nVehLeft="23" nVehSeen="25" meanSpeed="2.43" meanTimeLoss="31.19" meanOccupancy="7.78" maxOccupancy="18.80" meanMaxJamLengthInVehicles="2.22" meanMaxJamLengthInMeters="8.79" maxJamLengthInVehicles="6" maxJamLengthInMeters="31.31" jamLengthInVehiclesSum="666" jamLengthInMetersSum="2636.61" meanHaltingDuration="40.37" maxHaltingDuration="144.00" haltingDurationSum="767.00" meanIntervalHaltingDuration="35.95" maxIntervalHaltingDuration="102.00" intervalHaltingDurationSum="683.00" startedHalts="17.00" meanVehicleNumber="3.27" maxVehicleNumber="7" />
   <interval begin="2400.00" end="2700.00" id="e2_49" sampledSeconds="641.51" nVehEntered="18" nVehLeft="19" nVehSeen="20" meanSpeed="2.79" meanTimeLoss="25.37" meanOccupancy="6.04" maxOccupancy="23.70" meanMaxJamLengthInVehicles="1.45" meanMaxJamLengthInMeters="7.74" maxJamLengthInVehicles="6" maxJamLengthInMeters="28.59" jamLengthInVehiclesSum="436" jamLengthInMetersSum="2322.99" meanHaltingDuration="45.20" maxHaltingDuration="113.00" haltingDurationSum="452.00" meanIntervalHaltingDuration="44.50" maxIntervalHaltingDuration="106.00" intervalHaltingDurationSum="445.00" startedHalts="9.00" meanVehicleNumber="2.19" maxVehicleNumber="7" />
   <interval begin="2700.00" end="3000.00" id="e2_49" sampledSeconds="978.42" nVehEntered="15" nVehLeft="8" nVehSeen="16" meanSpeed="1.42" meanTimeLoss="53.59" meanOccupancy="10.49" maxOccupancy="22.60" meanMaxJamLengthInVehicles="2.49" meanMaxJamLengthInMeters="12.72" maxJamLengthInVehicles="5" maxJamLengthInMeters="26.62" jamLengthInVehiclesSum="747" jamLengthInMetersSum="3816.97" meanHaltingDuration="75.70" maxHaltingDuration="237.00" haltingDurationSum="757.00" meanIntervalHaltingDuration="75.70" maxIntervalHaltingDuration="237.00" intervalHaltingDurationSum="757.00" startedHalts="10.00" meanVehicleNumber="3.30" maxVehicleNumber="8" />
   <interval begin="3000.00" end="3300.00" id="e2_49" sampledSeconds="3688.79" nVehEntered="23" nVehLeft="30" nVehSeen="31" meanSpeed="0.71" meanTimeLoss="112.08" meanOccupancy="38.69" maxOccupancy="60.55" meanMaxJamLengthInVehicles="10.53" meanMaxJamLengthInMeters="54.54" maxJamLengthInVehicles="19" maxJamLengthInMeters="99.57" jamLengthInVehiclesSum="3240" jamLengthInMetersSum="16719.47" meanHaltingDuration="84.55" maxHaltingDuration="260.00" haltingDurationSum="3720.00" meanIntervalHaltingDuration="73.05" maxIntervalHaltingDuration="159.00" intervalHaltingDurationSum="3214.00" startedHalts="40.00" meanVehicleNumber="12.37" maxVehicleNumber="19" />
   <interval begin="3300.00" end="3600.00" id="e2_49" sampledSeconds="2661.42" nVehEntered="14" nVehLeft="0" nVehSeen="15" meanSpeed="0.33" meanTimeLoss="170.43" meanOccupancy="21.53" maxOccupancy="39.00" meanMaxJamLengthInVehicles="8.24" meanMaxJamLengthInMeters="37.19" maxJamLengthInVehicles="15" maxJamLengthInMeters="70.72" jamLengthInVehiclesSum="2471" jamLengthInMetersSum="11156.13" meanHaltingDuration="141.28" maxHaltingDuration="256.00" haltingDurationSum="2543.00" meanIntervalHaltingDuration="138.22" maxIntervalHaltingDuration="256.00" intervalHaltingDurationSum="2488.00" startedHalts="17.00" meanVehicleNumber="8.89" maxVehicleNumber="15" />
</detector>
