<?xml version="1.0" encoding="UTF-8"?>

<!-- generated on 2025-07-17 17:01:38 by Eclipse SUMO sumo Version 1.23.1
<sumoConfiguration xmlns:xsi="http://www.w3.org/2001/XMLSchema-instance" xsi:noNamespaceSchemaLocation="http://sumo.dlr.de/xsd/sumoConfiguration.xsd">

    <input>
        <net-file value="D:\TrafficSimulator\RL\rl-stsc\simulations/testmodel/osm.net.xml.gz"/>
        <route-files value="D:\TrafficSimulator\RL\rl-stsc\simulations/testmodel/osm.res_motorcycle.trips.xml"/>
        <additional-files value="D:\TrafficSimulator\RL\rl-stsc\simulations/testmodel/osm.add.xml"/>
    </input>

    <processing>
        <waiting-time-memory value="3600"/>
    </processing>

    <report>
        <no-warnings value="true"/>
        <duration-log.disable value="true"/>
        <no-step-log value="true"/>
    </report>

    <traci_server>
        <remote-port value="57122"/>
    </traci_server>

</sumoConfiguration>
-->

<detector xmlns:xsi="http://www.w3.org/2001/XMLSchema-instance" xsi:noNamespaceSchemaLocation="http://sumo.dlr.de/xsd/det_e2_file.xsd">
   <interval begin="0.00" end="300.00" id="e2_23" sampledSeconds="151.08" nVehEntered="8" nVehLeft="7" nVehSeen="8" meanSpeed="4.21" meanTimeLoss="12.79" meanOccupancy="1.09" maxOccupancy="4.40" meanMaxJamLengthInVehicles="0.28" meanMaxJamLengthInMeters="0.78" maxJamLengthInVehicles="2" maxJamLengthInMeters="6.91" jamLengthInVehiclesSum="85" jamLengthInMetersSum="234.53" meanHaltingDuration="18.00" maxHaltingDuration="25.00" haltingDurationSum="90.00" meanIntervalHaltingDuration="18.00" maxIntervalHaltingDuration="25.00" intervalHaltingDurationSum="90.00" startedHalts="5.00" meanVehicleNumber="0.52" maxVehicleNumber="2" />
   <interval begin="300.00" end="600.00" id="e2_23" sampledSeconds="109.32" nVehEntered="7" nVehLeft="8" nVehSeen="8" meanSpeed="5.91" meanTimeLoss="7.67" meanOccupancy="0.79" maxOccupancy="4.40" meanMaxJamLengthInVehicles="0.16" meanMaxJamLengthInMeters="0.34" maxJamLengthInVehicles="1" maxJamLengthInMeters="2.20" jamLengthInVehiclesSum="47" jamLengthInMetersSum="103.40" meanHaltingDuration="12.75" maxHaltingDuration="24.00" haltingDurationSum="51.00" meanIntervalHaltingDuration="12.75" maxIntervalHaltingDuration="24.00" intervalHaltingDurationSum="51.00" startedHalts="4.00" meanVehicleNumber="0.38" maxVehicleNumber="2" />
   <interval begin="600.00" end="900.00" id="e2_23" sampledSeconds="97.65" nVehEntered="7" nVehLeft="7" nVehSeen="7" meanSpeed="5.63" meanTimeLoss="7.72" meanOccupancy="0.70" maxOccupancy="4.40" meanMaxJamLengthInVehicles="0.14" meanMaxJamLengthInMeters="0.36" maxJamLengthInVehicles="2" maxJamLengthInMeters="6.95" jamLengthInVehiclesSum="41" jamLengthInMetersSum="107.79" meanHaltingDuration="11.25" maxHaltingDuration="24.00" haltingDurationSum="45.00" meanIntervalHaltingDuration="11.25" maxIntervalHaltingDuration="24.00" intervalHaltingDurationSum="45.00" startedHalts="4.00" meanVehicleNumber="0.34" maxVehicleNumber="2" />
   <interval begin="900.00" end="1200.00" id="e2_23" sampledSeconds="57.25" nVehEntered="4" nVehLeft="4" nVehSeen="4" meanSpeed="6.22" meanTimeLoss="7.47" meanOccupancy="0.41" maxOccupancy="2.20" meanMaxJamLengthInVehicles="0.08" meanMaxJamLengthInMeters="0.18" maxJamLengthInVehicles="1" maxJamLengthInMeters="2.20" jamLengthInVehiclesSum="24" jamLengthInMetersSum="52.80" meanHaltingDuration="25.00" maxHaltingDuration="25.00" haltingDurationSum="25.00" meanIntervalHaltingDuration="25.00" maxIntervalHaltingDuration="25.00" intervalHaltingDurationSum="25.00" startedHalts="1.00" meanVehicleNumber="0.20" maxVehicleNumber="1" />
</detector>
